country_named_entity_recognition/__init__.py
country_named_entity_recognition/common.py
country_named_entity_recognition/country_finder.py
country_named_entity_recognition/country_finder_spacy.py
country_named_entity_recognition-1.0.2.dist-info/licenses/LICENSE
country_named_entity_recognition-1.0.2.dist-info/METADATA
country_named_entity_recognition-1.0.2.dist-info/WHEEL
country_named_entity_recognition-1.0.2.dist-info/top_level.txt
country_named_entity_recognition-1.0.2.dist-info/RECORD
