Metadata-Version: 2.4
Name: country-named-entity-recognition
Version: 1.0.2
Summary: Finds countries in a string
Author: Thomas Wood
Maintainer: Thomas Wood
License-Expression: MIT
Project-URL: Homepage, https://fastdatascience.com/country-named-entity-recognition/
Keywords: country,ner,nlp,named entity recognition,natural language processing
Classifier: Development Status :: 3 - Alpha
Classifier: Intended Audience :: Developers
Classifier: Topic :: Software Development :: Build Tools
Classifier: Programming Language :: Python :: 3.9
Classifier: Programming Language :: Python :: 3.10
Classifier: Programming Language :: Python :: 3.10
Classifier: Programming Language :: Python :: 3.11
Classifier: Programming Language :: Python :: 3.12
Classifier: Programming Language :: Python :: 3.11
Classifier: Programming Language :: Python :: 3.13
Requires-Python: <4.0,>=3.9
License-File: LICENSE
Requires-Dist: pycountry>=24.6.1
Provides-Extra: test
Requires-Dist: pytest>=8.3.5; extra == "test"
Requires-Dist: spacy>=3.8.7; extra == "test"
Dynamic: license-file
